.DS_Store
nidataset/__init__.py
nidataset/_version.py
nidataset/draw.py
nidataset/preprocessing.py
nidataset/slices.py
nidataset/utility.py
nidataset/volume.py
nidataset-0.4.0.dist-info/licenses/LICENSE
nidataset-0.4.0.dist-info/METADATA
nidataset-0.4.0.dist-info/WHEEL
nidataset-0.4.0.dist-info/top_level.txt
nidataset-0.4.0.dist-info/RECORD
