Metadata-Version: 2.4
Name: nidataset
Version: 0.4.0
Summary: NIfTI dataset management package
Home-page: https://github.com/GiulioRusso/Ni-Dataset
Author: Giulio Russo, Ciro Russo
Author-email: russogiulio1998@icloud.com, ciro.russo2910@gmail.com
License: MIT License
Classifier: Programming Language :: Python :: 3
Classifier: License :: OSI Approved :: MIT License
Classifier: Operating System :: OS Independent
Requires-Python: >=3.8.0
License-File: LICENSE
Requires-Dist: nibabel>=5.0.0
Requires-Dist: numpy>=1.24
Requires-Dist: opencv-python>=4.7
Requires-Dist: pandas>=1.5
Requires-Dist: Pillow>=9.4
Requires-Dist: scipy>=1.10
Requires-Dist: SimpleITK>=2.2
Requires-Dist: scikit-image>=0.19
Requires-Dist: tqdm>=4.64
Dynamic: author
Dynamic: author-email
Dynamic: classifier
Dynamic: description
Dynamic: description-content-type
Dynamic: home-page
Dynamic: license
Dynamic: license-file
Dynamic: requires-dist
Dynamic: requires-python
Dynamic: summary
